replit_keep_alive/__init__.py
replit_keep_alive/keep_alive.py
replit_keep_alive-1.2.0.dist-info/LICENSE
replit_keep_alive-1.2.0.dist-info/METADATA
replit_keep_alive-1.2.0.dist-info/WHEEL
replit_keep_alive-1.2.0.dist-info/top_level.txt
replit_keep_alive-1.2.0.dist-info/RECORD
