Metadata-Version: 2.1
Name: replit-keep-alive
Version: 1.2.0
Summary: Create a simple Flask webserver to keep your Repl online using a pinger. (such as https://up.rdsl.ga/)
Home-page: https://github.com/Raadsl/Replit-keep-alive-pypi
Author: Raadsel
Author-email: iraadsel@gmail.com
Classifier: Programming Language :: Python :: 3
Classifier: License :: OSI Approved :: ISC License (ISCL)
Classifier: Operating System :: OS Independent
Requires-Python: >=3.6
License-File: LICENSE
